libear/__init__.py
libear/config.h.in
libear/ear.c
libscanbuild/__init__.py
libscanbuild/analyze.py
libscanbuild/arguments.py
libscanbuild/clang.py
libscanbuild/compilation.py
libscanbuild/intercept.py
libscanbuild/report.py
libscanbuild/resources/scanview.css
libscanbuild/resources/selectable.js
libscanbuild/resources/sorttable.js
scan_build-2.0.20.dist-info/LICENSE.txt
scan_build-2.0.20.dist-info/METADATA
scan_build-2.0.20.dist-info/WHEEL
scan_build-2.0.20.dist-info/entry_points.txt
scan_build-2.0.20.dist-info/top_level.txt
scan_build-2.0.20.dist-info/RECORD
