Metadata-Version: 2.1
Name: scan-build
Version: 2.0.20
Summary: static code analyzer wrapper for Clang.
Home-page: https://github.com/rizsotto/scan-build
Author: László Nagy
Author-email: rizsotto@gmail.com
License: LICENSE.txt
Keywords: Clang,scan-build,static analyzer
Platform: UNKNOWN
Classifier: Development Status :: 5 - Production/Stable
Classifier: License :: OSI Approved :: University of Illinois/NCSA Open Source License
Classifier: Environment :: Console
Classifier: Operating System :: POSIX
Classifier: Operating System :: MacOS :: MacOS X
Classifier: Intended Audience :: Developers
Classifier: Programming Language :: C
Classifier: Programming Language :: Python :: 3
Classifier: Programming Language :: Python :: 3.6
Classifier: Programming Language :: Python :: 3.7
Classifier: Programming Language :: Python :: 3.8
Classifier: Programming Language :: Python :: 3.9
Classifier: Topic :: Software Development :: Compilers
Classifier: Topic :: Software Development :: Quality Assurance
Requires-Python: >=3.6
